helium_py/__init__.py
helium_py/version.py
helium_py/api/__init__.py
helium_py/api/accounts.py
helium_py/api/api.py
helium_py/api/assert_locations.py
helium_py/api/blocks.py
helium_py/api/chain_variables.py
helium_py/api/challenges.py
helium_py/api/cities.py
helium_py/api/client.py
helium_py/api/constants.py
helium_py/api/dc_burns.py
helium_py/api/decorators.py
helium_py/api/elections.py
helium_py/api/hotspots.py
helium_py/api/locations.py
helium_py/api/oracle_prices.py
helium_py/api/ouis.py
helium_py/api/pending_transactions.py
helium_py/api/rewards.py
helium_py/api/state_channels.py
helium_py/api/stats.py
helium_py/api/transactions.py
helium_py/api/validators.py
helium_py/crypto/__init__.py
helium_py/crypto/address.py
helium_py/crypto/constants.py
helium_py/crypto/keypair.py
helium_py/crypto/mnemonic.py
helium_py/crypto/utils.py
helium_py/crypto/wordlists/__init__.py
helium_py/crypto/wordlists/english.py
helium_py/currency/__init__.py
helium_py/currency/balance.py
helium_py/currency/exceptions.py
helium_py/currency/types.py
helium_py/onboarding/__init__.py
helium_py/onboarding/client.py
helium_py/onboarding/constants.py
helium_py/proto/__init__.py
helium_py/proto/local/__init__.py
helium_py/proto/longfi/__init__.py
helium_py/proto/radio/__init__.py
helium_py/test/__init__.py
helium_py/test/utils.py
helium_py/transactions/__init__.py
helium_py/transactions/add_gateway_v1.py
helium_py/transactions/assert_location_v1.py
helium_py/transactions/assert_location_v2.py
helium_py/transactions/decorators.py
helium_py/transactions/mixins.py
helium_py/transactions/payment.py
helium_py/transactions/payment_v1.py
helium_py/transactions/payment_v2.py
helium_py/transactions/security_exchange_v1.py
helium_py/transactions/stake_validator_v1.py
helium_py/transactions/token_burn_v1.py
helium_py/transactions/transaction.py
helium_py/transactions/transfer_hotspot_v1.py
helium_py/transactions/transfer_hotspot_v2.py
helium_py/transactions/transfer_validator_stake_v1.py
helium_py-0.2a2.dist-info/LICENSE
helium_py-0.2a2.dist-info/METADATA
helium_py-0.2a2.dist-info/WHEEL
helium_py-0.2a2.dist-info/top_level.txt
helium_py-0.2a2.dist-info/RECORD
