Metadata-Version: 2.1
Name: helium-py
Version: 0.2a2
Summary: Official python lib for interacting with the Helium blockchain
Author-email: Joshua Miller <joshua@cryptoballoon.net>, Joe Cronyn <joe@cryptoballoon.net>
Maintainer-email: Joshua Miller <joshua@cryptoballoon.net>, Joe Cronyn <joe@cryptoballoon.net>
License: Apache-2.0
Classifier: Development Status :: 2 - Pre-Alpha
Classifier: Intended Audience :: Developers
Classifier: Operating System :: POSIX :: Linux
Classifier: Programming Language :: Python :: 3.7
Classifier: Programming Language :: Python :: 3.8
Classifier: Programming Language :: Python :: 3.9
Classifier: Programming Language :: Python :: 3.10
Classifier: License :: OSI Approved :: MIT License
Requires-Python: >=3.7
License-File: LICENSE
Requires-Dist: requests (<3,>=2.26.0)
Requires-Dist: betterproto[compiler] (<3,>=2.0.0b4)
Requires-Dist: pynacl (>=1.5.0)
Requires-Dist: base58 (==2.1.1)
Requires-Dist: importlib-metadata (>=1.0) ; python_version < "3.8"
